MANIFEST.in
README.md
setup.py
aethos/__init__.py
aethos/__main__.py
aethos/analysis.py
aethos/cli.py
aethos/helpers.py
aethos/util.py
aethos.egg-info/PKG-INFO
aethos.egg-info/SOURCES.txt
aethos.egg-info/dependency_links.txt
aethos.egg-info/entry_points.txt
aethos.egg-info/requires.txt
aethos.egg-info/top_level.txt
aethos/cleaning/__init__.py
aethos/cleaning/categorical.py
aethos/cleaning/clean.py
aethos/cleaning/numeric.py
aethos/cleaning/test_unittest.py
aethos/cleaning/util.py
aethos/config/__init__.py
aethos/config/config.py
aethos/config/config.yml
aethos/config/config_init.py
aethos/config/user_config.py
aethos/feature_engineering/__init__.py
aethos/feature_engineering/feature.py
aethos/feature_engineering/test_unittest.py
aethos/feature_engineering/text.py
aethos/feature_engineering/util.py
aethos/model_analysis/__init__.py
aethos/model_analysis/classification_model_analysis.py
aethos/model_analysis/constants.py
aethos/model_analysis/model_analysis.py
aethos/model_analysis/model_explanation.py
aethos/model_analysis/regression_model_analysis.py
aethos/model_analysis/test_unittest.py
aethos/model_analysis/text_model_analysis.py
aethos/model_analysis/unsupervised_model_analysis.py
aethos/modelling/__init__.py
aethos/modelling/classification_models.py
aethos/modelling/model.py
aethos/modelling/regression_models.py
aethos/modelling/test_unittest.py
aethos/modelling/text.py
aethos/modelling/unsupervised_models.py
aethos/modelling/util.py
aethos/preprocessing/__init__.py
aethos/preprocessing/numeric.py
aethos/preprocessing/preprocess.py
aethos/preprocessing/test_unittest.py
aethos/preprocessing/text.py
aethos/stats/__init__.py
aethos/stats/stats.py
aethos/stats/test_unittest.py
aethos/stats/util.py
aethos/templates/__init__.py
aethos/templates/template_generator.py
aethos/templates/util.py
aethos/templates/files/Dockerfile
aethos/templates/files/main
aethos/templates/files/requirements.txt
aethos/visualizations/__init__.py
aethos/visualizations/test_unittest.py
aethos/visualizations/util.py
aethos/visualizations/visualizations.py
aethos/visualizations/visualize.py