Metadata-Version: 2.1
Name: aethos
Version: 2.0.0
Summary: A library of data science and machine learning techniques to help automate your workflow.
Home-page: https://github.com/Ashton-Sidhu/aethos
Author: Ashton Sidhu
Author-email: ashton.sidhu1994@gmail.com
License: GPL-3.0
Keywords: datascience,machinelearning,automation,analysis
Platform: UNKNOWN
Classifier: Programming Language :: Python :: 3.6
Classifier: Programming Language :: Python :: 3.7
Classifier: Development Status :: 4 - Beta
Requires-Python: >= 3.6
Provides-Extra: ptmodels
